{"country":{"AF":"Afghanistan","AL":"Albania","DZ":"Algeria","AD":"Andorra","AO":"Angola","AI":"Anguilla","AG":"Antigua and Barbuda","AR":"Argentina","AM":"Armenia","AW":"Aruba","AU":"Australia","AT":"Austria","AZ":"Azerbaijan","BS":"Bahamas","BH":"Bahrain","BD":"Bangladesh","BB":"Barbados","BY":"Belarus","BE":"Belgium","BZ":"Belize","BJ":"Benin","BM":"Bermuda","BT":"Bhutan","BO":"Bolivia","BA":"Bosnia and Herzegovina","BW":"Botswana","BR":"Brazil","BN":"Brunei Darussalam","BG":"Bulgaria","BF":"Burkina Faso","BI":"Burundi","KH":"Cambodia","CM":"Cameroon","CA":"Canada","CV":"Cape Verde","CF":"Central African Republic","TD":"Chad","CL":"Chile","CN":"China","CO":"Colombia","KM":"Comoros","CG":"Congo","CD":"Congo, Democratic Republic of the Congo","CR":"Costa Rica","CI":"Cote D'Ivoire","HR":"Croatia","CU":"Cuba","CW":"Curacao","CY":"Cyprus","CZ":"Czech Republic","DK":"Denmark","DJ":"Djibouti","DM":"Dominica","DO":"Dominican Republic","EC":"Ecuador","EG":"Egypt","SV":"El Salvador","GQ":"Equatorial Guinea","ER":"Eritrea","EE":"Estonia","ET":"Ethiopia","FO":"Faroe Islands","FJ":"Fiji","FI":"Finland","FR":"France","GF":"French Guiana","PF":"French Polynesia","TF":"French Southern Territories","GA":"Gabon","GM":"Gambia","GE":"Georgia","DE":"Germany","GH":"Ghana","GI":"Gibraltar","GR":"Greece","GL":"Greenland","GD":"Grenada","GP":"Guadeloupe","GU":"Guam","GT":"Guatemala","GG":"Guernsey","GN":"Guinea","GW":"Guinea-Bissau","GY":"Guyana","HT":"Haiti","HN":"Honduras","HK":"Hong Kong","HU":"Hungary","IS":"Iceland","IN":"India","ID":"Indonesia","IR":"Iran, Islamic Republic of","IQ":"Iraq","IE":"Ireland","IL":"Israel","IT":"Italy","JM":"Jamaica","JP":"Japan","JE":"Jersey","JO":"Jordan","KZ":"Kazakhstan","KE":"Kenya","KI":"Kiribati","KP":"Korea, Democratic People's Republic of","KR":"Korea, Republic of","XK":"Kosovo","KW":"Kuwait","KG":"Kyrgyzstan","LA":"Lao People's Democratic Republic","LV":"Latvia","LB":"Lebanon","LS":"Lesotho","LR":"Liberia","LY":"Libyan Arab Jamahiriya","LI":"Liechtenstein","LT":"Lithuania","LU":"Luxembourg","MO":"Macao","MK":"Macedonia, the Former Yugoslav Republic of","MG":"Madagascar","MW":"Malawi","MY":"Malaysia","MV":"Maldives","ML":"Mali","MT":"Malta","MH":"Marshall Islands","MQ":"Martinique","MR":"Mauritania","MU":"Mauritius","YT":"Mayotte","MX":"Mexico","FM":"Micronesia, Federated States of","MD":"Moldova, Republic of","MC":"Monaco","MN":"Mongolia","ME":"Montenegro","MS":"Montserrat","MA":"Morocco","MZ":"Mozambique","MM":"Myanmar","NA":"Namibia","NR":"Nauru","NP":"Nepal","NL":"Netherlands","NC":"New Caledonia","NZ":"New Zealand","NI":"Nicaragua","NE":"Niger","NG":"Nigeria","NU":"Niue","NF":"Norfolk Island","MP":"Northern Mariana Islands","NO":"Norway","OM":"Oman","PK":"Pakistan","PW":"Palau","PS":"Palestinian Territory, Occupied","PA":"Panama","PG":"Papua New Guinea","PY":"Paraguay","PE":"Peru","PH":"Philippines","PN":"Pitcairn","PL":"Poland","PT":"Portugal","PR":"Puerto Rico","QA":"Qatar","RE":"Reunion","RO":"Romania","RU":"Russian Federation","RW":"Rwanda","BL":"Saint Barthelemy","SH":"Saint Helena","KN":"Saint Kitts and Nevis","LC":"Saint Lucia","MF":"Saint Martin","PM":"Saint Pierre and Miquelon","VC":"Saint Vincent and the Grenadines","WS":"Samoa","SM":"San Marino","ST":"Sao Tome and Principe","SA":"Saudi Arabia","SN":"Senegal","RS":"Serbia","CS":"Serbia and Montenegro","SC":"Seychelles","SL":"Sierra Leone","SG":"Singapore","SX":"Sint Maarten","SK":"Slovakia","SI":"Slovenia","SB":"Solomon Islands","SO":"Somalia","ZA":"South Africa","GS":"South Georgia and the South Sandwich Islands","SS":"South Sudan","ES":"Spain","LK":"Sri Lanka","SD":"Sudan","SR":"Suriname","SJ":"Svalbard and Jan Mayen","SZ":"Swaziland","SE":"Sweden","CH":"Switzerland","SY":"Syrian Arab Republic","TW":"Taiwan, Province of China","TJ":"Tajikistan","TZ":"Tanzania","TH":"Thailand","TL":"Timor-Leste","TG":"Togo","TK":"Tokelau","TO":"Tonga","TT":"Trinidad and Tobago","TN":"Tunisia","TR":"Turkey","TM":"Turkmenistan","TC":"Turks and Caicos Islands","TV":"Tuvalu","UG":"Uganda","UA":"Ukraine","AE":"United Arab Emirates","GB":"United Kingdom","US":"United States","UM":"United States Minor Outlying Islands","UY":"Uruguay","UZ":"Uzbekistan","VU":"Vanuatu","VE":"Venezuela","VN":"Viet Nam","VG":"Virgin Islands, British","VI":"Virgin Islands, U.s.","WF":"Wallis and Futuna","EH":"Western Sahara","YE":"Yemen","ZM":"Zambia","ZW":"Zimbabwe"},
"states":{"US":[
    {"value":"AK", "name":"Alaska"},
    {"value":"AL", "name":"Alabama"},
    {"value":"AR", "name":"Arkansas"},
    {"value":"AS", "name":"American Samoa"},
    {"value":"AZ", "name":"Arizona"},
    {"value":"CA", "name":"California"},
    {"value":"CO", "name":"Colorado"},
    {"value":"CT", "name":"Connecticut"},
    {"value":"DC", "name":"D.C"},
    {"value":"DE", "name":"Delaware"},
    {"value":"FL", "name":"Florida"},
    {"value":"GA", "name":"Georgia"},
    {"value":"GU", "name":"Guam"},
    {"value":"HI", "name":"Hawaii"},
    {"value":"IA", "name":"Iowa"},
    {"value":"ID", "name":"Idaho"},
    {"value":"IL", "name":"Illinois"},
    {"value":"IN", "name":"Indiana"},
    {"value":"KS", "name":"Kansas"},
    {"value":"KY", "name":"Kentucky"},
    {"value":"LA", "name":"Louisiana"},
    {"value":"MA", "name":"Massachusetts"},
    {"value":"MD", "name":"Maryland"},
    {"value":"ME", "name":"Maine"},
    {"value":"MH", "name":"Marshall Islands"},
    {"value":"MI", "name":"Michigan"},
    {"value":"MN", "name":"Minnesota"},
    {"value":"MO", "name":"Missouri"},
    {"value":"MP", "name":"Marianas"},
    {"value":"MS", "name":"Mississippi"},
    {"value":"MT", "name":"Montana"},
    {"value":"NC", "name":"North Carolina"},
    {"value":"ND", "name":"North Dakota"},
    {"value":"NE", "name":"Nebraska"},
    {"value":"NH", "name":"New Hampshire"},
    {"value":"NJ", "name":"New Jersey"},
    {"value":"NM", "name":"New Mexico"},
    {"value":"NV", "name":"Nevada"},
    {"value":"NY", "name":"New York"},
    {"value":"OH", "name":"Ohio"},
    {"value":"OK", "name":"Oklahoma"},
    {"value":"OR", "name":"Oregon"},
    {"value":"PA", "name":"Pennsylvania"},
    {"value":"PW", "name":"Palau"},
    {"value":"RI", "name":"Rhode Island"},
    {"value":"SC", "name":"South Carolina"},
    {"value":"SD", "name":"South Dakota"},
    {"value":"TN", "name":"Tennessee"},
    {"value":"TX", "name":"Texas"},
    {"value":"UT", "name":"Utah"},
    {"value":"VA", "name":"Virginia"},
    {"value":"VI", "name":"Virgin Islands"},
    {"value":"VT", "name":"Vermont"},
    {"value":"WA", "name":"Washington"},
    {"value":"WI", "name":"Wisconsin"},
    {"value":"WV", "name":"West Virginia"},
    {"value":"WY", "name":"Wyoming"},
    {"value":"AA", "name":"Military Americas"},
    {"value":"AE", "name":"Military Europe/ME/Canada"},
    {"value":"AP", "name":"Military Pacific"}
],
"CA":[
    {"value": "AB", "name":"Alberta"},
    {"value": "MB", "name":"Manitoba"},
    {"value": "AB", "name":"Alberta"},
    {"value": "BC", "name":"British Columbia"},
    {"value": "MB", "name":"Manitoba"},
    {"value": "NB", "name":"New Brunswick"},
    {"value": "NL", "name":"Newfoundland and Labrador"},
    {"value": "NS", "name":"Nova Scotia"},
    {"value": "NT", "name":"Northwest Territories"},
    {"value": "NU", "name":"Nunavut"},
    {"value": "ON", "name":"Ontario"},
    {"value": "PE", "name":"Prince Edward Island"},
    {"value": "QC", "name":"Quebec"},
    {"value": "SK", "name":"Saskatchewan"},
    {"value": "YT", "name":"Yukon Territory"}
],
"AU":
[
    {"value": "AAT", "name": "Australian Antarctic Territory"},
    {"value": "ACT", "name": "Australian Capital Territory"},
    {"value": "NT", "name": "Northern Territory"},
    {"value": "NSW", "name": "New South Wales"},
    {"value": "QLD", "name": "Queensland"},
    {"value": "SA", "name": "South Australia"},
    {"value": "TAS", "name": "Tasmania"},
    {"value": "VIC", "name": "Victoria"},
    {"value": "WA", "name": "Western Australia"}
],
"BR":[
    {"value": "AC", "name": "Acre"},
    {"value": "AL", "name": "Alagoas"},
    {"value": "AM", "name": "Amazonas"},
    {"value": "AP", "name": "Amapa"},
    {"value": "BA", "name": "Baia"},
    {"value": "CE", "name": "Ceara"},
    {"value": "DF", "name": "Distrito Federal"},
    {"value": "ES", "name": "Espirito Santo"},
    {"value": "FN", "name": "Fernando de Noronha"},
    {"value": "GO", "name": "Goias"},
    {"value": "MA", "name": "Maranhao"},
    {"value": "MG", "name": "Minas Gerais"},
    {"value": "MS", "name": "Mato Grosso do Sul"},
    {"value": "MT", "name": "Mato Grosso"},
    {"value": "PA", "name": "Para"},
    {"value": "PB", "name": "Paraiba"},
    {"value": "PE", "name": "Pernambuco"},
    {"value": "PI", "name": "Piaui"},
    {"value": "PR", "name": "Parana"},
    {"value": "RJ", "name": "Rio de Janeiro"},
    {"value": "RN", "name": "Rio Grande do Norte"},
    {"value": "RO", "name": "Rondonia"},
    {"value": "RR", "name": "Roraima"},
    {"value": "RS", "name": "Rio Grande do Sul"},
    {"value": "SC", "name": "Santa Catarina"},
    {"value": "SE", "name": "Sergipe"},
    {"value": "SP", "name": "Sao Paulo"},
    {"value": "TO", "name": "Tocatins"}
],
"NL":[
    {"value": "DR", "name":"Drente"},
    {"value": "FL", "name":"Flevoland"},
    {"value": "FR", "name":"Friesland"},
    {"value": "GL", "name":"Gelderland"},
    {"value": "GR", "name":"Groningen"},
    {"value": "LB", "name":"Limburg"},
    {"value": "NB", "name":"Noord Brabant"},
    {"value": "NH", "name":"Noord Holland"},
    {"value": "OV", "name":"Overijssel"},
    {"value": "UT", "name":"Utrecht"},
    {"value": "ZH", "name":"Zuid Holland"},
    {"value": "ZL", "name":"Zeeland"}
],
"UK":[
    {"value": "AVON", "name":"Avon"},
    {"value": "ABERD", "name":"Aberdeenshire"},
    {"value": "BEDS", "name":"Bedfordshire"},
    {"value": "BERKS", "name":"Berkshire"},
    {"value": "BUCKS", "name":"Buckinghamshire"},
    {"value": "CAMBS", "name":"Cambridgeshire"},
    {"value": "CHESH", "name":"Cheshire"},
    {"value": "CLEVE", "name":"Cleveland"},
    {"value": "CORN", "name":"Cornwall"},
    {"value": "CUMB", "name":"Cumbria"},
    {"value": "DERBY", "name":"Derbyshire"},
    {"value": "DEVON", "name":"Devon"},
    {"value": "DORSET", "name":"Dorset"},
    {"value": "DURHAM", "name":"Durham"},
    {"value": "ESSEX", "name":"Essex"},
    {"value": "GLOUS", "name":"Gloucestershire"},
    {"value": "GGLASG", "name":"Greater Glasgow"},
    {"value": "GLONDON", "name":"Greater London"},
    {"value": "GMANCH", "name":"Greater Manchester"},
    {"value": "HANTS", "name":"Hampshire"},
    {"value": "HERWOR", "name":"Hereford & Worcestershire"},
    {"value": "HERTS", "name":"Hertfordshire"},
    {"value": "HUMBER", "name":"Humberside"},
    {"value": "IOM", "name":"Isle of Man"},
    {"value": "IOW", "name":"Isle of Wight"},
    {"value": "KENT", "name":"Kent"},
    {"value": "LANCS", "name":"Lancashire"},
    {"value": "LEICS", "name":"Leicestershire"},
    {"value": "LINCS", "name":"Lincolnshire"},
    {"value": "MERSEY", "name":"Merseyside"},
    {"value": "NORF", "name":"Norfolk"},
    {"value": "NHANTS", "name":"Northamptonshire"},
    {"value": "NTHUMB", "name":"Northumberland"},
    {"value": "NOTTS", "name":"Nottinghamshire"},
    {"value": "OXON", "name":"Oxfordshire"},
    {"value": "SCT", "name":"Scotland"},
    {"value": "SHROPS", "name":"Shropshire"},
    {"value": "SOM", "name":"Somerset"},
    {"value": "STAFFS", "name":"Staffordshire"},
    {"value": "SUFF", "name":"Suffolk"},
    {"value": "SURREY", "name":"Surrey"},
    {"value": "SUSS", "name":"Sussex"},
    {"value": "WARKS", "name":"Warwickshire"},
    {"value": "WMID", "name":"West Midlands"},
    {"value": "WILTS", "name":"Wiltshire"},
    {"value": "YORK", "name":"Yorkshire"}
],
"EI":[
    {"value": "CO ANTRIM", "name": "County Antrim"},
    {"value": "CO ARMAGH", "name": "County Armagh"},
    {"value": "CO DOWN", "name": "County Down"},
    {"value": "CO FERMANAGH", "name": "County Fermanagh"},
    {"value": "CO DERRY", "name": "County Londonderry"},
    {"value": "CO TYRONE", "name": "County Tyrone"},
    {"value": "CO CAVAN", "name": "County Cavan"},
    {"value": "CO DONEGAL", "name": "County Donegal"},
    {"value": "CO MONAGHAN", "name": "County Monaghan"},
    {"value": "CO DUBLIN", "name": "County Dublin"},
    {"value": "CO CARLOW", "name": "County Carlow"},
    {"value": "CO KILDARE", "name": "County Kildare"},
    {"value": "CO KILKENNY", "name": "County Kilkenny"},
    {"value": "CO LAOIS", "name": "County Laois"},
    {"value": "CO LONGFORD", "name": "County Longford"},
    {"value": "CO LOUTH", "name": "County Louth"},
    {"value": "CO MEATH", "name": "County Meath"},
    {"value": "CO OFFALY", "name": "County Offaly"},
    {"value": "CO WESTMEATH", "name": "County Westmeath"},
    {"value": "CO WEXFORD", "name": "County Wexford"},
    {"value": "CO WICKLOW", "name": "County Wicklow"},
    {"value": "CO GALWAY", "name": "County Galway"},
    {"value": "CO MAYO", "name": "County Mayo"},
    {"value": "CO LEITRIM", "name": "County Leitrim"},
    {"value": "CO ROSCOMMON", "name": "County Roscommon"},
    {"value": "CO SLIGO", "name": "County Sligo"},
    {"value": "CO CLARE", "name": "County Clare"},
    {"value": "CO CORK", "name": "County Cork"},
    {"value": "CO KERRY", "name": "County Kerry"},
    {"value": "CO LIMERICK", "name": "County Limerick"},
    {"value": "CO TIPPERARY", "name": "County Tipperary"},
    {"value": "CO WATERFORD", "name": "County Waterford"}
]}}